azure/mgmt/migrationassessment/__init__.py
azure/mgmt/migrationassessment/_configuration.py
azure/mgmt/migrationassessment/_migration_assessment_mgmt_client.py
azure/mgmt/migrationassessment/_patch.py
azure/mgmt/migrationassessment/_serialization.py
azure/mgmt/migrationassessment/_version.py
azure/mgmt/migrationassessment/py.typed
azure/mgmt/migrationassessment/aio/__init__.py
azure/mgmt/migrationassessment/aio/_configuration.py
azure/mgmt/migrationassessment/aio/_migration_assessment_mgmt_client.py
azure/mgmt/migrationassessment/aio/_patch.py
azure/mgmt/migrationassessment/aio/operations/__init__.py
azure/mgmt/migrationassessment/aio/operations/_assessed_machines_operations_operations.py
azure/mgmt/migrationassessment/aio/operations/_assessed_sql_database_v2_operations_operations.py
azure/mgmt/migrationassessment/aio/operations/_assessed_sql_instance_v2_operations_operations.py
azure/mgmt/migrationassessment/aio/operations/_assessed_sql_machines_operations_operations.py
azure/mgmt/migrationassessment/aio/operations/_assessed_sql_recommended_entity_operations_operations.py
azure/mgmt/migrationassessment/aio/operations/_assessment_options_operations_operations.py
azure/mgmt/migrationassessment/aio/operations/_assessment_project_summary_operations_operations.py
azure/mgmt/migrationassessment/aio/operations/_assessment_projects_operations_operations.py
azure/mgmt/migrationassessment/aio/operations/_assessments_operations_operations.py
azure/mgmt/migrationassessment/aio/operations/_avs_assessed_machines_operations_operations.py
azure/mgmt/migrationassessment/aio/operations/_avs_assessment_options_operations_operations.py
azure/mgmt/migrationassessment/aio/operations/_avs_assessments_operations_operations.py
azure/mgmt/migrationassessment/aio/operations/_groups_operations_operations.py
azure/mgmt/migrationassessment/aio/operations/_hyperv_collectors_operations_operations.py
azure/mgmt/migrationassessment/aio/operations/_import_collectors_operations_operations.py
azure_mgmt_migrationassessment-1.0.0b1.dist-info/LICENSE
azure_mgmt_migrationassessment-1.0.0b1.dist-info/METADATA
azure_mgmt_migrationassessment-1.0.0b1.dist-info/WHEEL
azure_mgmt_migrationassessment-1.0.0b1.dist-info/top_level.txt
azure_mgmt_migrationassessment-1.0.0b1.dist-info/RECORD
